<annotation>
	<folder></folder>
	<filename>---------------605-_png.rf.67fd1508f7c0cddd3a52c3ce02235f85.jpg</filename>
	<path>---------------605-_png.rf.67fd1508f7c0cddd3a52c3ce02235f85.jpg</path>
	<source>
		<database>roboflow.ai</database>
	</source>
	<size>
		<width>1920</width>
		<height>1080</height>
		<depth>3</depth>
	</size>
	<segmented>0</segmented>
	<object>
		<name>plate</name>
		<pose>Unspecified</pose>
		<truncated>0</truncated>
		<difficult>0</difficult>
		<occluded>0</occluded>
		<bndbox>
			<xmin>627</xmin>
			<xmax>780</xmax>
			<ymin>289</ymin>
			<ymax>365</ymax>
		</bndbox>
	</object>
	<object>
		<name>plate</name>
		<pose>Unspecified</pose>
		<truncated>0</truncated>
		<difficult>0</difficult>
		<occluded>0</occluded>
		<bndbox>
			<xmin>1033</xmin>
			<xmax>1104</xmax>
			<ymin>270</ymin>
			<ymax>327</ymax>
		</bndbox>
	</object>
</annotation>
