<annotation>
	<folder></folder>
	<filename>---------------592-_png.rf.874b7b3612368f5cf2e736e85c5c061e.jpg</filename>
	<path>---------------592-_png.rf.874b7b3612368f5cf2e736e85c5c061e.jpg</path>
	<source>
		<database>roboflow.ai</database>
	</source>
	<size>
		<width>1920</width>
		<height>1080</height>
		<depth>3</depth>
	</size>
	<segmented>0</segmented>
	<object>
		<name>plate</name>
		<pose>Unspecified</pose>
		<truncated>0</truncated>
		<difficult>0</difficult>
		<occluded>0</occluded>
		<bndbox>
			<xmin>482</xmin>
			<xmax>591</xmax>
			<ymin>197</ymin>
			<ymax>256</ymax>
		</bndbox>
	</object>
</annotation>
