<annotation>
	<folder></folder>
	<filename>---------------666-_png.rf.ee502fe6b1990736d925ea4f2bf55378.jpg</filename>
	<path>---------------666-_png.rf.ee502fe6b1990736d925ea4f2bf55378.jpg</path>
	<source>
		<database>roboflow.ai</database>
	</source>
	<size>
		<width>1920</width>
		<height>1080</height>
		<depth>3</depth>
	</size>
	<segmented>0</segmented>
	<object>
		<name>plate</name>
		<pose>Unspecified</pose>
		<truncated>0</truncated>
		<difficult>0</difficult>
		<occluded>0</occluded>
		<bndbox>
			<xmin>287</xmin>
			<xmax>443</xmax>
			<ymin>444</ymin>
			<ymax>507</ymax>
		</bndbox>
	</object>
	<object>
		<name>plate</name>
		<pose>Unspecified</pose>
		<truncated>0</truncated>
		<difficult>0</difficult>
		<occluded>0</occluded>
		<bndbox>
			<xmin>967</xmin>
			<xmax>1038</xmax>
			<ymin>321</ymin>
			<ymax>362</ymax>
		</bndbox>
	</object>
</annotation>
